export_manager/__init__.py
export_manager/__main__.py
export_manager/_fsutil.py
export_manager/_interval.py
export_manager/cli.py
export_manager/dataset.py
export_manager/report.py
export_manager-0.0.5.dist-info/LICENSE
export_manager-0.0.5.dist-info/METADATA
export_manager-0.0.5.dist-info/WHEEL
export_manager-0.0.5.dist-info/entry_points.txt
export_manager-0.0.5.dist-info/top_level.txt
export_manager-0.0.5.dist-info/RECORD
