Metadata-Version: 2.1
Name: export-manager
Version: 0.0.5
Summary: A tool for managing automated exports of personal data
Home-page: https://github.com/brokensandals/export_manager
Author: Jacob Williams
Author-email: jacobaw@gmail.com
License: UNKNOWN
Platform: UNKNOWN
Classifier: Programming Language :: Python :: 3
Classifier: License :: OSI Approved :: MIT License
Classifier: Operating System :: OS Independent
Requires-Python: >=3.7
Requires-Dist: gitdb (>=4)
Requires-Dist: GitPython (>=3.1)
Requires-Dist: toml (>=0.10)
